qrack/__init__.py
qrack/qasm_simulator.py
cirqqrack-0.8.5.dist-info/LICENSE
cirqqrack-0.8.5.dist-info/METADATA
cirqqrack-0.8.5.dist-info/WHEEL
cirqqrack-0.8.5.dist-info/top_level.txt
cirqqrack-0.8.5.dist-info/RECORD
