Metadata-Version: 2.2
Name: cirqqrack
Version: 0.8.5
Summary: Cirq Qrack Plugin - Qrack High-Performance GPU simulation for Cirq
Home-page: https://github.com/vm6502q/cirq-qrack
Author: Daniel Strano
Author-email: stranoj@gmail.com
License: Apache 2.0
Keywords: cirq qrack simulator quantum addon backend
Classifier: Environment :: Console
Classifier: License :: OSI Approved :: Apache Software License
Classifier: Intended Audience :: Developers
Classifier: Intended Audience :: Science/Research
Classifier: Operating System :: Microsoft :: Windows
Classifier: Operating System :: MacOS
Classifier: Operating System :: POSIX :: Linux
Classifier: Programming Language :: C++
Classifier: Programming Language :: Python :: 3.5
Classifier: Programming Language :: Python :: 3.6
Classifier: Programming Language :: Python :: 3.7
Classifier: Programming Language :: Python :: 3.8
Classifier: Topic :: Scientific/Engineering
License-File: LICENSE
Requires-Dist: pyqrack>=1.30.0
Dynamic: author
Dynamic: author-email
Dynamic: classifier
Dynamic: description
Dynamic: description-content-type
Dynamic: home-page
Dynamic: keywords
Dynamic: license
Dynamic: requires-dist
Dynamic: summary
